odoo/addons/delivery_carrier_info/README.rst
odoo/addons/delivery_carrier_info/__init__.py
odoo/addons/delivery_carrier_info/__manifest__.py
odoo/addons/delivery_carrier_info/i18n/delivery_carrier_info.pot
odoo/addons/delivery_carrier_info/i18n/es.po
odoo/addons/delivery_carrier_info/i18n/it.po
odoo/addons/delivery_carrier_info/models/__init__.py
odoo/addons/delivery_carrier_info/models/delivery_carrier.py
odoo/addons/delivery_carrier_info/readme/CONTRIBUTORS.md
odoo/addons/delivery_carrier_info/readme/DESCRIPTION.md
odoo/addons/delivery_carrier_info/readme/USAGE.md
odoo/addons/delivery_carrier_info/static/description/icon.png
odoo/addons/delivery_carrier_info/static/description/index.html
odoo/addons/delivery_carrier_info/views/delivery_view.xml
odoo_addon_delivery_carrier_info-18.0.1.0.0.2.dist-info/METADATA
odoo_addon_delivery_carrier_info-18.0.1.0.0.2.dist-info/WHEEL
odoo_addon_delivery_carrier_info-18.0.1.0.0.2.dist-info/top_level.txt
odoo_addon_delivery_carrier_info-18.0.1.0.0.2.dist-info/RECORD
